diversedata/__init__.py
diversedata/data/bcindigenousbiz.csv
diversedata/data/genderassessment.csv
diversedata/data/globalrights.csv
diversedata/data/hcmst.csv
diversedata/data/wildfire.csv
diversedata/data/womensmarchmadness.csv
diversedata/data_descriptions/bcindigenousbiz.txt
diversedata/data_descriptions/genderassessment.txt
diversedata/data_descriptions/globalrights.txt
diversedata/data_descriptions/hcmst.txt
diversedata/data_descriptions/wildfire.txt
diversedata/data_descriptions/womensmarchmadness.txt
diversedata/diversedata.py
diversedata-1.0.3.dist-info/METADATA
diversedata-1.0.3.dist-info/WHEEL
diversedata-1.0.3.dist-info/licenses/LICENSE.md
diversedata-1.0.3.dist-info/RECORD
