Metadata-Version: 2.4
Name: diversedata
Version: 1.0.3
Summary: A Python package that provides a curated collection of real-world data sets centered on themes of equity, diversity and inclusion (EDI). These data sets are intended to support teaching, learning, and analysis by offering meaningful and socially relevant data that can be used in data science workflows.
License: MIT
License-File: LICENSE.md
Author: Katie Burak, Elham E. Khoda, and Stephanie Ta
Requires-Python: >=3.12
Classifier: License :: OSI Approved :: MIT License
Classifier: Programming Language :: Python :: 3
Classifier: Programming Language :: Python :: 3.12
Classifier: Programming Language :: Python :: 3.13
Classifier: Programming Language :: Python :: 3.14
Requires-Dist: pandas (>=2.3.1)
